{
    "Entities": [
        {},
        {},
        {
            "Sprite": {
                "r": 1.0,
                "g": 1.0,
                "b": 1.0,
                "a": 1.0,
                "layer": 0,
                "assetID": 14757395258967641292
            },
            "Transform": {
                "posX": 0.0,
                "posY": 0.0,
                "posZ": -40.0,
                "rotX": 0.0,
                "rotY": 0.0,
                "rotZ": 0.0,
                "scaleX": 350.0,
                "scaleY": 120.0,
                "scaleZ": 0.0,
                "elipse": false
            }
        },
        {
            "Animation": {
                "assetID": 403168095096,
                "currFrame": 2,
                "speed": 0.07999999821186066,
                "currState": 1
            },
            "Collider": {
                "collider": 0,
                "posX": -70.0,
                "posY": -105.0,
                "rotation": 0.0,
                "dimX": 7.5,
                "dimY": 15.0
            },
            "Gravity": {
                "x": 0.0,
                "y": -90.0
            },
            "RigidBody": {
                "dimX": 15.0,
                "dimY": 15.0,
                "rotation": 0.0,
                "mass": 10.0,
                "posX": -70.0,
                "posY": -105.0,
                "lockRotate": true
            },
            "Script": {
                "script": "ObjectPlayer"
            },
            "Sprite": {
                "r": 1.0,
                "g": 1.0,
                "b": 1.0,
                "a": 1.0,
                "layer": 2,
                "assetID": 14757395258967641292
            },
            "Tag": {
                "Tag": "Player"
            },
            "Text": {
                "fontName": "Lato",
                "scale": 0.05999999865889549,
                "text": "Player",
                "coloX": 1.0,
                "coloY": 1.0,
                "coloZ": 0.0
            },
            "Transform": {
                "posX": -70.0,
                "posY": -105.0,
                "posZ": -150.0,
                "rotX": 0.0,
                "rotY": 0.0,
                "rotZ": 0.0,
                "scaleX": 15.0,
                "scaleY": 15.0,
                "scaleZ": 15.0,
                "elipse": false
            }
        },
        {
            "Animation": {
                "assetID": 14757395258967641292,
                "currFrame": 2,
                "speed": 0.07999999821186066,
                "currState": 1
            },
            "Collider": {
                "collider": 0,
                "posX": 40.0,
                "posY": -88.0,
                "rotation": 0.0,
                "dimX": 7.5,
                "dimY": 15.0
            },
            "Gravity": {
                "x": 0.0,
                "y": -90.0
            },
            "RigidBody": {
                "dimX": 15.0,
                "dimY": 15.0,
                "rotation": 0.0,
                "mass": 10.0,
                "posX": 40.0,
                "posY": -88.0,
                "lockRotate": true
            },
            "Script": {
                "script": "ObjectBasicEnemy"
            },
            "Sprite": {
                "r": 1.0,
                "g": 0.0,
                "b": 0.0,
                "a": 1.0,
                "layer": 2,
                "assetID": 14757395258967641292
            },
            "Tag": {
                "Tag": "Enemy"
            },
            "Text": {
                "fontName": "Getho",
                "scale": 0.05999999865889549,
                "text": "Enemy",
                "coloX": 1.0,
                "coloY": 1.0,
                "coloZ": 0.0
            },
            "Transform": {
                "posX": 40.0,
                "posY": -88.0,
                "posZ": -150.0,
                "rotX": 0.0,
                "rotY": 0.0,
                "rotZ": 0.0,
                "scaleX": 15.0,
                "scaleY": 15.0,
                "scaleZ": 15.0,
                "elipse": false
            }
        },
        {},
        {},
        {
            "Sprite": {
                "r": 1.0,
                "g": 1.0,
                "b": 1.0,
                "a": 1.0,
                "layer": 0,
                "assetID": 14757395258967641292
            },
            "Transform": {
                "posX": -122.30045318603516,
                "posY": 117.56405639648438,
                "posZ": -40.0,
                "rotX": 0.0,
                "rotY": 0.0,
                "rotZ": 0.0,
                "scaleX": 350.0,
                "scaleY": 120.0,
                "scaleZ": 0.0,
                "elipse": false
            }
        },
        {
            "Animation": {
                "assetID": 1053176620760,
                "currFrame": 1,
                "speed": 0.07999999821186066,
                "currState": 1
            },
            "Collider": {
                "collider": 0,
                "posX": -70.0,
                "posY": -105.0,
                "rotation": 0.0,
                "dimX": 7.5,
                "dimY": 15.0
            },
            "Gravity": {
                "x": 0.0,
                "y": -90.0
            },
            "RigidBody": {
                "dimX": 15.0,
                "dimY": 15.0,
                "rotation": 0.0,
                "mass": 10.0,
                "posX": -70.0,
                "posY": -105.0,
                "lockRotate": true
            },
            "Script": {
                "script": "ObjectPlayer"
            },
            "Sprite": {
                "r": 1.0,
                "g": 1.0,
                "b": 1.0,
                "a": 1.0,
                "layer": 2,
                "assetID": 14757395258967641292
            },
            "Tag": {
                "Tag": "Player"
            },
            "Text": {
                "fontName": "Lato",
                "scale": 0.05999999865889549,
                "text": "Player",
                "coloX": 1.0,
                "coloY": 1.0,
                "coloZ": 0.0
            },
            "Transform": {
                "posX": -70.0,
                "posY": -105.0,
                "posZ": -150.0,
                "rotX": 0.0,
                "rotY": 0.0,
                "rotZ": 0.0,
                "scaleX": 15.0,
                "scaleY": 15.0,
                "scaleZ": 15.0,
                "elipse": false
            }
        },
        {
            "Animation": {
                "assetID": 14757395258967641292,
                "currFrame": 2,
                "speed": 0.07999999821186066,
                "currState": 1
            },
            "Collider": {
                "collider": 0,
                "posX": 40.0,
                "posY": -88.0,
                "rotation": 0.0,
                "dimX": 7.5,
                "dimY": 15.0
            },
            "Gravity": {
                "x": 0.0,
                "y": -90.0
            },
            "RigidBody": {
                "dimX": 15.0,
                "dimY": 15.0,
                "rotation": 0.0,
                "mass": 10.0,
                "posX": 40.0,
                "posY": -88.0,
                "lockRotate": true
            },
            "Script": {
                "script": "ObjectBasicEnemy"
            },
            "Sprite": {
                "r": 1.0,
                "g": 0.0,
                "b": 0.0,
                "a": 1.0,
                "layer": 2,
                "assetID": 14757395258967641292
            },
            "Tag": {
                "Tag": "Enemy"
            },
            "Text": {
                "fontName": "Getho",
                "scale": 0.05999999865889549,
                "text": "Enemy",
                "coloX": 1.0,
                "coloY": 1.0,
                "coloZ": 0.0
            },
            "Transform": {
                "posX": 40.0,
                "posY": -88.0,
                "posZ": -150.0,
                "rotX": 0.0,
                "rotY": 0.0,
                "rotZ": 0.0,
                "scaleX": -15.0,
                "scaleY": 15.0,
                "scaleZ": 15.0,
                "elipse": false
            }
        },
        {},
        {},
        {
            "Sprite": {
                "r": 1.0,
                "g": 1.0,
                "b": 1.0,
                "a": 1.0,
                "layer": 0,
                "assetID": 14757395258967641292
            },
            "Transform": {
                "posX": -16.61920928955078,
                "posY": 141.41766357421875,
                "posZ": -40.0,
                "rotX": 0.0,
                "rotY": 0.0,
                "rotZ": 0.0,
                "scaleX": 350.0,
                "scaleY": 120.0,
                "scaleZ": 0.0,
                "elipse": false
            }
        },
        {
            "Animation": {
                "assetID": 239225268792,
                "currFrame": 3,
                "speed": 0.07999999821186066,
                "currState": 1
            },
            "Collider": {
                "collider": 0,
                "posX": -70.0,
                "posY": -105.0,
                "rotation": 0.0,
                "dimX": 7.5,
                "dimY": 15.0
            },
            "Gravity": {
                "x": 0.0,
                "y": -90.0
            },
            "RigidBody": {
                "dimX": 15.0,
                "dimY": 15.0,
                "rotation": 0.0,
                "mass": 10.0,
                "posX": -70.0,
                "posY": -105.0,
                "lockRotate": true
            },
            "Script": {
                "script": "ObjectPlayer"
            },
            "Sprite": {
                "r": 1.0,
                "g": 1.0,
                "b": 1.0,
                "a": 1.0,
                "layer": 2,
                "assetID": 14757395258967641292
            },
            "Tag": {
                "Tag": "Player"
            },
            "Text": {
                "fontName": "Lato",
                "scale": 0.05999999865889549,
                "text": "Player",
                "coloX": 1.0,
                "coloY": 1.0,
                "coloZ": 0.0
            },
            "Transform": {
                "posX": -70.0,
                "posY": -105.0,
                "posZ": -150.0,
                "rotX": 0.0,
                "rotY": 0.0,
                "rotZ": 0.0,
                "scaleX": 15.0,
                "scaleY": 15.0,
                "scaleZ": 15.0,
                "elipse": false
            }
        },
        {
            "Animation": {
                "assetID": 14757395258967641292,
                "currFrame": 3,
                "speed": 0.07999999821186066,
                "currState": 1
            },
            "Collider": {
                "collider": 0,
                "posX": 40.0,
                "posY": -88.0,
                "rotation": 0.0,
                "dimX": 7.5,
                "dimY": 15.0
            },
            "Gravity": {
                "x": 0.0,
                "y": -90.0
            },
            "RigidBody": {
                "dimX": 15.0,
                "dimY": 15.0,
                "rotation": 0.0,
                "mass": 10.0,
                "posX": 40.0,
                "posY": -88.0,
                "lockRotate": true
            },
            "Script": {
                "script": "ObjectBasicEnemy"
            },
            "Sprite": {
                "r": 1.0,
                "g": 0.0,
                "b": 0.0,
                "a": 0.0,
                "layer": 2,
                "assetID": 14757395258967641292
            },
            "Tag": {
                "Tag": "Enemy"
            },
            "Text": {
                "fontName": "Getho",
                "scale": 0.05999999865889549,
                "text": "Enemy",
                "coloX": 1.0,
                "coloY": 1.0,
                "coloZ": 0.0
            },
            "Transform": {
                "posX": 40.0,
                "posY": -88.0,
                "posZ": -150.0,
                "rotX": 0.0,
                "rotY": 0.0,
                "rotZ": 0.0,
                "scaleX": 15.0,
                "scaleY": 15.0,
                "scaleZ": 15.0,
                "elipse": false
            }
        },
        {},
        {},
        {
            "Sprite": {
                "r": 1.0,
                "g": 1.0,
                "b": 1.0,
                "a": 1.0,
                "layer": 0,
                "assetID": 14757395258967641292
            },
            "Transform": {
                "posX": 2.556812286376953,
                "posY": 164.4193115234375,
                "posZ": -40.0,
                "rotX": 0.0,
                "rotY": 0.0,
                "rotZ": 0.0,
                "scaleX": 350.0,
                "scaleY": 120.0,
                "scaleZ": 0.0,
                "elipse": false
            }
        },
        {
            "Collider": {
                "collider": 0,
                "posX": 0.0,
                "posY": -128.0,
                "rotation": 0.0,
                "dimX": 256.0,
                "dimY": 5.0
            },
            "Gravity": {
                "x": 0.0,
                "y": -10.0
            },
            "RigidBody": {
                "dimX": 256.0,
                "dimY": 5.0,
                "rotation": 0.0,
                "mass": 3.4028234663852886e38,
                "posX": 0.0,
                "posY": -128.0,
                "lockRotate": false
            },
            "Transform": {
                "posX": 0.0,
                "posY": -128.0,
                "posZ": 1.0,
                "rotX": 0.0,
                "rotY": 0.0,
                "rotZ": 0.0,
                "scaleX": 256.0,
                "scaleY": 5.0,
                "scaleZ": 1.0,
                "elipse": false
            }
        },
        {
            "Collider": {
                "collider": 0,
                "posX": -128.0,
                "posY": 0.0,
                "rotation": 0.0,
                "dimX": 5.0,
                "dimY": 249.60000610351563
            },
            "Gravity": {
                "x": 0.0,
                "y": -10.0
            },
            "RigidBody": {
                "dimX": 5.0,
                "dimY": 249.60000610351563,
                "rotation": 0.0,
                "mass": 3.4028234663852886e38,
                "posX": -128.0,
                "posY": 0.0,
                "lockRotate": false
            },
            "Transform": {
                "posX": -128.0,
                "posY": 0.0,
                "posZ": 1.0,
                "rotX": 0.0,
                "rotY": 0.0,
                "rotZ": 0.0,
                "scaleX": 5.0,
                "scaleY": 256.0,
                "scaleZ": 1.0,
                "elipse": false
            }
        },
        {
            "Collider": {
                "collider": 0,
                "posX": 128.0,
                "posY": 0.0,
                "rotation": 0.0,
                "dimX": 5.0,
                "dimY": 249.60000610351563
            },
            "Gravity": {
                "x": 0.0,
                "y": -10.0
            },
            "RigidBody": {
                "dimX": 5.0,
                "dimY": 249.60000610351563,
                "rotation": 0.0,
                "mass": 3.4028234663852886e38,
                "posX": 128.0,
                "posY": 0.0,
                "lockRotate": false
            },
            "Transform": {
                "posX": 128.0,
                "posY": 0.0,
                "posZ": 1.0,
                "rotX": 0.0,
                "rotY": 0.0,
                "rotZ": 0.0,
                "scaleX": 5.0,
                "scaleY": 256.0,
                "scaleZ": 1.0,
                "elipse": false
            }
        },
        {
            "Collider": {
                "collider": 0,
                "posX": 0.0,
                "posY": -123.0,
                "rotation": 0.0,
                "dimX": 251.0,
                "dimY": 3.0
            },
            "Gravity": {
                "x": 0.0,
                "y": -10.0
            },
            "RigidBody": {
                "dimX": 251.0,
                "dimY": 3.0,
                "rotation": 0.0,
                "mass": 3.4028234663852886e38,
                "posX": 0.0,
                "posY": -123.0,
                "lockRotate": false
            },
            "Sprite": {
                "r": 0.0,
                "g": 2.384185791015625e-7,
                "b": 1.0,
                "a": 1.0,
                "layer": 2,
                "assetID": 14757395258967641292
            },
            "Tag": {
                "Tag": "Platform"
            },
            "Transform": {
                "posX": 0.0,
                "posY": -123.0,
                "posZ": 1.0,
                "rotX": 0.0,
                "rotY": 0.0,
                "rotZ": 0.0,
                "scaleX": 251.0,
                "scaleY": 3.0,
                "scaleZ": 1.0,
                "elipse": false
            }
        },
        {
            "Collider": {
                "collider": 0,
                "posX": -38.0,
                "posY": -78.0,
                "rotation": 0.0,
                "dimX": 20.0,
                "dimY": 30.0
            },
            "Gravity": {
                "x": 0.0,
                "y": -10.0
            },
            "RigidBody": {
                "dimX": 20.0,
                "dimY": 30.0,
                "rotation": 0.0,
                "mass": 3.4028234663852886e38,
                "posX": -38.0,
                "posY": -78.0,
                "lockRotate": false
            },
            "Sprite": {
                "r": 1.0,
                "g": 1.0,
                "b": 0.0,
                "a": 1.0,
                "layer": 2,
                "assetID": 14757395258967641292
            },
            "Tag": {
                "Tag": "Platform"
            },
            "Transform": {
                "posX": -38.0,
                "posY": -78.0,
                "posZ": 1.0,
                "rotX": 0.0,
                "rotY": 0.0,
                "rotZ": 0.0,
                "scaleX": 20.0,
                "scaleY": 30.0,
                "scaleZ": 1.0,
                "elipse": false
            }
        },
        {
            "Collider": {
                "collider": 0,
                "posX": 38.0,
                "posY": -100.55574035644531,
                "rotation": 0.0,
                "dimX": 90.0,
                "dimY": 3.0
            },
            "Gravity": {
                "x": 0.0,
                "y": -10.0
            },
            "RigidBody": {
                "dimX": 90.0,
                "dimY": 3.0,
                "rotation": 0.0,
                "mass": 3.4028234663852886e38,
                "posX": 38.0,
                "posY": -98.0,
                "lockRotate": false
            },
            "Sprite": {
                "r": 1.0,
                "g": 0.0,
                "b": 0.0,
                "a": 1.0,
                "layer": 2,
                "assetID": 14757395258967641292
            },
            "Tag": {
                "Tag": "Platform"
            },
            "Transform": {
                "posX": 38.0,
                "posY": -100.55574035644531,
                "posZ": 1.0,
                "rotX": 0.0,
                "rotY": 0.0,
                "rotZ": 0.0,
                "scaleX": 90.0,
                "scaleY": 3.0,
                "scaleZ": 1.0,
                "elipse": false
            }
        },
        {
            "Collider": {
                "collider": 0,
                "posX": 38.0,
                "posY": -48.0,
                "rotation": 0.0,
                "dimX": 90.0,
                "dimY": 3.0
            },
            "Gravity": {
                "x": 0.0,
                "y": -10.0
            },
            "RigidBody": {
                "dimX": 90.0,
                "dimY": 3.0,
                "rotation": 0.0,
                "mass": 3.4028234663852886e38,
                "posX": 38.0,
                "posY": -48.0,
                "lockRotate": false
            },
            "Sprite": {
                "r": 1.0,
                "g": 0.0,
                "b": 0.0,
                "a": 1.0,
                "layer": 2,
                "assetID": 14757395258967641292
            },
            "Tag": {
                "Tag": "Platform"
            },
            "Transform": {
                "posX": 38.0,
                "posY": -48.0,
                "posZ": 1.0,
                "rotX": 0.0,
                "rotY": 0.0,
                "rotZ": 0.0,
                "scaleX": 90.0,
                "scaleY": 3.0,
                "scaleZ": 1.0,
                "elipse": false
            }
        },
        {
            "Animation": {
                "assetID": 14757395258967641292,
                "currFrame": 3,
                "speed": 0.07999999821186066,
                "currState": 1
            },
            "Collider": {
                "collider": 0,
                "posX": -70.0,
                "posY": -105.0,
                "rotation": 0.0,
                "dimX": 7.5,
                "dimY": 15.0
            },
            "Gravity": {
                "x": 0.0,
                "y": -90.0
            },
            "RigidBody": {
                "dimX": 15.0,
                "dimY": 15.0,
                "rotation": 0.0,
                "mass": 10.0,
                "posX": -70.0,
                "posY": -105.0,
                "lockRotate": true
            },
            "Script": {
                "script": "ObjectPlayer"
            },
            "Sprite": {
                "r": 1.0,
                "g": 1.0,
                "b": 1.0,
                "a": 1.0,
                "layer": 2,
                "assetID": 14757395258967641292
            },
            "Tag": {
                "Tag": "Player"
            },
            "Text": {
                "fontName": "Lato",
                "scale": 0.05999999865889549,
                "text": "Player",
                "coloX": 1.0,
                "coloY": 1.0,
                "coloZ": 0.0
            },
            "Transform": {
                "posX": -70.0,
                "posY": -105.0,
                "posZ": -150.0,
                "rotX": 0.0,
                "rotY": 0.0,
                "rotZ": 0.0,
                "scaleX": 15.0,
                "scaleY": 15.0,
                "scaleZ": 15.0,
                "elipse": false
            }
        },
        {
            "Animation": {
                "assetID": 14757395258967641292,
                "currFrame": 3,
                "speed": 0.07999999821186066,
                "currState": 1
            },
            "Collider": {
                "collider": 0,
                "posX": 40.0,
                "posY": -88.0,
                "rotation": 0.0,
                "dimX": 7.5,
                "dimY": 15.0
            },
            "Gravity": {
                "x": 0.0,
                "y": -90.0
            },
            "RigidBody": {
                "dimX": 15.0,
                "dimY": 15.0,
                "rotation": 0.0,
                "mass": 10.0,
                "posX": 40.0,
                "posY": -88.0,
                "lockRotate": true
            },
            "Script": {
                "script": "ObjectBasicEnemy"
            },
            "Sprite": {
                "r": 1.0,
                "g": 0.0,
                "b": 0.0,
                "a": 0.0,
                "layer": 2,
                "assetID": 14757395258967641292
            },
            "Tag": {
                "Tag": "Enemy"
            },
            "Text": {
                "fontName": "Getho",
                "scale": 0.05999999865889549,
                "text": "Enemy",
                "coloX": 1.0,
                "coloY": 1.0,
                "coloZ": 0.0
            },
            "Transform": {
                "posX": 40.0,
                "posY": -88.0,
                "posZ": -150.0,
                "rotX": 0.0,
                "rotY": 0.0,
                "rotZ": 0.0,
                "scaleX": 15.0,
                "scaleY": 15.0,
                "scaleZ": 15.0,
                "elipse": false
            }
        },
        {
            "Collider": {
                "collider": 0,
                "posX": 50.0,
                "posY": 20.0,
                "rotation": 0.0,
                "dimX": 30.0,
                "dimY": 5.0
            },
            "Sprite": {
                "r": 1.0,
                "g": 1.0,
                "b": 1.0,
                "a": 1.0,
                "layer": 2,
                "assetID": 14757395258967641292
            },
            "Tag": {
                "Tag": "FinishAddingNodes"
            },
            "Text": {
                "fontName": "Lato",
                "scale": 0.029999999329447746,
                "text": "Finish Adding Nodes",
                "coloX": 0.0,
                "coloY": 0.0,
                "coloZ": 0.0
            },
            "Transform": {
                "posX": 50.0,
                "posY": 20.0,
                "posZ": 1.0,
                "rotX": 0.0,
                "rotY": 0.0,
                "rotZ": 0.0,
                "scaleX": 30.0,
                "scaleY": 5.0,
                "scaleZ": 5.0,
                "elipse": false
            }
        },
        {
            "Collider": {
                "collider": 0,
                "posX": 90.0,
                "posY": 20.0,
                "rotation": 0.0,
                "dimX": 30.0,
                "dimY": 5.0
            },
            "Sprite": {
                "r": 1.0,
                "g": 1.0,
                "b": 1.0,
                "a": 1.0,
                "layer": 2,
                "assetID": 14757395258967641292
            },
            "Tag": {
                "Tag": "ResetNodes"
            },
            "Text": {
                "fontName": "Lato",
                "scale": 0.029999999329447746,
                "text": "Reset Nodes",
                "coloX": 0.0,
                "coloY": 0.0,
                "coloZ": 0.0
            },
            "Transform": {
                "posX": 90.0,
                "posY": 20.0,
                "posZ": 1.0,
                "rotX": 0.0,
                "rotY": 0.0,
                "rotZ": 0.0,
                "scaleX": 30.0,
                "scaleY": 5.0,
                "scaleZ": 5.0,
                "elipse": false
            }
        }
    ]
}